rai_sim/__init__.py
rai_sim/launch_manager.py
rai_sim/o3de/o3de_bridge.py
rai_sim/simulation_bridge.py
rai_sim/tools.py
rai_sim-0.0.2.dist-info/METADATA
rai_sim-0.0.2.dist-info/WHEEL
rai_sim-0.0.2.dist-info/RECORD
