Metadata-Version: 2.3
Name: rai-sim
Version: 0.0.2
Summary: Package to run simulations
Author: Jakub Matejczyk
Author-email: jakub.matejczyk@robotec.ai
Requires-Python: >=3.10,<3.13
Classifier: Development Status :: 4 - Beta
Classifier: License :: OSI Approved :: Apache Software License
Classifier: Programming Language :: Python :: 3
Classifier: Programming Language :: Python :: 3.10
Classifier: Programming Language :: Python :: 3.11
Classifier: Programming Language :: Python :: 3.12
Requires-Dist: PyYAML
Requires-Dist: rai_core (>=2.0.0.a2,<3.0.0)
